updategempa/__init__.py
Earthquakeupdate_indonesia-0.6.dist-info/LICENSE
Earthquakeupdate_indonesia-0.6.dist-info/METADATA
Earthquakeupdate_indonesia-0.6.dist-info/WHEEL
Earthquakeupdate_indonesia-0.6.dist-info/top_level.txt
Earthquakeupdate_indonesia-0.6.dist-info/RECORD
